LICENSE
MANIFEST.in
README.rst
setup.cfg
setup.py
versioneer.py
artellapipe/__init__.py
artellapipe/dccs/__init__.py
artellapipe/dccs/maya/__init__.py
artellapipe/dccs/maya/__logging__.ini
artellapipe/dccs/maya/__version__.py
artellapipe/dccs/maya/_version.py
artellapipe/dccs/maya/loader.py
artellapipe/dccs/maya/register.py
artellapipe/dccs/maya/core/__init__.py
artellapipe/dccs/maya/core/sequencer.py
artellapipe/dccs/maya/core/toolbox.py
artellapipe/dccs/maya/managers/__init__.py
artellapipe/dccs/maya/managers/dependencies.py
artellapipe/dccs/maya/managers/playblasts.py
artellapipe_dccs_maya.egg-info/PKG-INFO
artellapipe_dccs_maya.egg-info/SOURCES.txt
artellapipe_dccs_maya.egg-info/dependency_links.txt
artellapipe_dccs_maya.egg-info/not-zip-safe
artellapipe_dccs_maya.egg-info/requires.txt
artellapipe_dccs_maya.egg-info/top_level.txt
tests/__init__.py
tests/test_general.py