Metadata-Version: 2.1
Name: artellapipe-dccs-maya
Version: 0.0.15
Summary: Maya libraries for ArtellaPipe
Home-page: https://github.com/ArtellaPipe/artellapipe-dccs-maya
Author: Tomas Poveda
Author-email: tpovedatd@gmail.com
License: MIT
Platform: UNKNOWN
Provides-Extra: dev
Provides-Extra: test
